tap_mssql/__init__.py
tap_mssql/connection.py
tap_mssql/sync_strategies/__init__.py
tap_mssql/sync_strategies/common.py
tap_mssql/sync_strategies/full_table.py
tap_mssql/sync_strategies/incremental.py
tap_mssql/sync_strategies/logical.py
firebend_tap_mssql-1.0.5.dist-info/LICENSE
firebend_tap_mssql-1.0.5.dist-info/METADATA
firebend_tap_mssql-1.0.5.dist-info/WHEEL
firebend_tap_mssql-1.0.5.dist-info/entry_points.txt
firebend_tap_mssql-1.0.5.dist-info/top_level.txt
firebend_tap_mssql-1.0.5.dist-info/RECORD
