Metadata-Version: 2.1
Name: firebend-tap-mssql
Version: 1.0.5
Summary: Singer.io tap for extracting data from SQL Server - PipelineWise compatible
Home-page: https://github.com/firebend/pipelinewise-tap-mssql
Author: Stitch, wintersrd, SteveDMurphy, degreed-data-engineering, Firebend
License: UNKNOWN
Platform: UNKNOWN
Classifier: License :: OSI Approved :: GNU Affero General Public License v3
Classifier: Programming Language :: Python :: 3 :: Only
License-File: LICENSE
Requires-Dist: pendulum (~=1.5.1)
Requires-Dist: singer-python (~=5.12.2)
Requires-Dist: sqlalchemy (~=1.4.31)
Requires-Dist: pyodbc (==4.0.32)
Requires-Dist: backoff (==1.8.0)
Requires-Dist: MarkupSafe (==2.0.1)
Requires-Dist: jinja2 (==2.11.3)
Provides-Extra: test
Requires-Dist: pylint (~=2.12.2) ; extra == 'test'
Requires-Dist: pytest (~=6.2.5) ; extra == 'test'
Requires-Dist: pytest-cov (~=3.0.0) ; extra == 'test'
